p4rrot/__init__.py
p4rrot/checks.py
p4rrot/generator_tools.py
p4rrot/known_types.py
p4rrot/standard_fields.py
p4rrot/core/__init__.py
p4rrot/core/commands.py
p4rrot/core/stateful.py
p4rrot/tofino/__init__.py
p4rrot/v1model/__init__.py
p4rrot-0.0.1.dist-info/LICENSE
p4rrot-0.0.1.dist-info/METADATA
p4rrot-0.0.1.dist-info/WHEEL
p4rrot-0.0.1.dist-info/top_level.txt
p4rrot-0.0.1.dist-info/RECORD
