Metadata-Version: 2.1
Name: p4rrot
Version: 0.0.1
Summary: Generating P4 Code for the Application Layer
Home-page: https://github.com/gycsaba96/P4RROT
Author: Csaba Gyorgyi
Author-email: gycsaba96@gmail.com
License: UNKNOWN
Project-URL: Bug Tracker, https://github.com/gycsaba96/P4RROT/issues
Platform: UNKNOWN
Classifier: Programming Language :: Python :: 3
Classifier: License :: OSI Approved :: MIT License
Classifier: Operating System :: OS Independent
Requires-Python: >=3.6
License-File: LICENSE
